Metadata-Version: 1.0
Name: three-distributions
Version: 1.0
Summary: Generic, Gaussian and Binomial distributions
Home-page: UNKNOWN
Author: Riya Lodha
Author-email: UNKNOWN
License: UNKNOWN
Platform: UNKNOWN
